Metadata-Version: 2.1
Name: spoticonnect
Version: 0.2
Summary: Python package to control Spotify and Spotify Connect without requiring spotify locally installed
Home-page: https://github.com/aerospeace/spoticonnect
Author: Hicham Tahiri
License: BSD
Download-URL: https://github.com/aerospeace/spoticonnect/tarball/0.2
Platform: UNKNOWN
Classifier: Development Status :: 3 - Alpha
Classifier: Intended Audience :: Developers
Classifier: Programming Language :: Python :: 3
Requires-Python: >=3.5
